b2b_sdk/__init__.py
b2b_sdk/client.py
b2b_sdk/exceptions.py
b2b_sdk/models.py
b2b_sdk/utils.py
tests/__init__.py
tests/test_client.py
tests/test_utils.py
b2b_api_sdk-0.1.4.dist-info/LICENSE
b2b_api_sdk-0.1.4.dist-info/METADATA
b2b_api_sdk-0.1.4.dist-info/WHEEL
b2b_api_sdk-0.1.4.dist-info/top_level.txt
b2b_api_sdk-0.1.4.dist-info/RECORD
